cerebra/__init__.py
cerebra/commandline.py
cerebra/count_variants.py
cerebra/find_peptide_variants.py
cerebra/germline_filter.py
cerebra/os_utils.py
cerebra/protein_variant_predictor.py
cerebra/utils.py
cerebra-1.2.0.dist-info/LICENSE
cerebra-1.2.0.dist-info/METADATA
cerebra-1.2.0.dist-info/WHEEL
cerebra-1.2.0.dist-info/entry_points.txt
cerebra-1.2.0.dist-info/top_level.txt
cerebra-1.2.0.dist-info/RECORD
