Metadata-Version: 2.1
Name: cerebra
Version: 1.2.0
Summary: finds mutants in your scRNA-seq experiment
Home-page: https://github.com/czbiohub/cerebra
Author: Lincoln Harris
Author-email: ljharris018@gmail.com
License: MIT
Keywords: cerebra
Platform: UNKNOWN
Classifier: Development Status :: 4 - Beta
Classifier: Intended Audience :: Developers
Classifier: Intended Audience :: Science/Research
Classifier: Topic :: Scientific/Engineering :: Bio-Informatics
Classifier: License :: OSI Approved :: MIT License
Classifier: Natural Language :: English
Classifier: Operating System :: Unix
Classifier: Operating System :: MacOS
Classifier: Programming Language :: Python :: 3.6
Classifier: Programming Language :: Python :: 3.7
Classifier: Programming Language :: Python :: 3.8
Requires-Dist: biopython (==1.77)
Requires-Dist: click
Requires-Dist: cython (==0.29.13)
Requires-Dist: hgvs
Requires-Dist: ncls
Requires-Dist: numpy
Requires-Dist: pandas
Requires-Dist: pathos
Requires-Dist: pyfaidx
Requires-Dist: setuptools (>=38.6.0)
Requires-Dist: tqdm
Requires-Dist: vcfpy
